paelladoc/__init__.py
paelladoc/dependencies.py
paelladoc/adapters/__init__.py
paelladoc/adapters/input/__init__.py
paelladoc/adapters/output/__init__.py
paelladoc/adapters/output/chroma/chroma_vector_store_adapter.py
paelladoc/adapters/output/filesystem/taxonomy_provider.py
paelladoc/adapters/output/filesystem/taxonomy_repository.py
paelladoc/adapters/output/sqlite/config_models.py
paelladoc/adapters/output/sqlite/configuration_adapter.py
paelladoc/adapters/output/sqlite/db_models.py
paelladoc/adapters/output/sqlite/mapper.py
paelladoc/adapters/output/sqlite/models.py
paelladoc/adapters/output/sqlite/sqlite_memory_adapter.py
paelladoc/adapters/persistence/__init__.py
paelladoc/adapters/plugins/__init__.py
paelladoc/adapters/plugins/code/__init__.py
paelladoc/adapters/plugins/code/code_generation.py
paelladoc/adapters/plugins/code/generate_context.py
paelladoc/adapters/plugins/code/generate_doc.py
paelladoc/adapters/plugins/core/__init__.py
paelladoc/adapters/plugins/core/continue_proj.py
paelladoc/adapters/plugins/core/help.py
paelladoc/adapters/plugins/core/paella.py
paelladoc/adapters/plugins/core/project_crud.py
paelladoc/adapters/plugins/core/project_utils.py
paelladoc/adapters/plugins/core/verification.py
paelladoc/adapters/plugins/memory/__init__.py
paelladoc/adapters/plugins/memory/project_memory.py
paelladoc/adapters/plugins/product/__init__.py
paelladoc/adapters/plugins/product/product_management.py
paelladoc/adapters/plugins/styles/__init__.py
paelladoc/adapters/plugins/styles/coding_styles.py
paelladoc/adapters/plugins/styles/git_workflows.py
paelladoc/adapters/plugins/templates/__init__.py
paelladoc/adapters/plugins/templates/templates.py
paelladoc/adapters/services/system_time_service.py
paelladoc/application/__init__.py
paelladoc/application/services/memory_service.py
paelladoc/application/services/vector_store_service.py
paelladoc/application/utils/behavior_enforcer.py
paelladoc/config/database.py
paelladoc/domain/__init__.py
paelladoc-0.3.7.dist-info/METADATA
paelladoc-0.3.7.dist-info/WHEEL
paelladoc-0.3.7.dist-info/licenses/LICENSE
paelladoc-0.3.7.dist-info/licenses/LICENSE-COMMERCIAL.txt
paelladoc-0.3.7.dist-info/RECORD
