Metadata-Version: 2.4
Name: paelladoc
Version: 0.3.7
Summary: AI-First Development Framework - An MCP Implementation
Project-URL: Homepage, https://paelladoc.com
Project-URL: Documentation, https://docs.paelladoc.com
Project-URL: Repository, https://github.com/jlcases/paelladoc
Project-URL: Bug Tracker, https://github.com/jlcases/paelladoc/issues
Author-email: jlcases <jl@paelladoc.com>
License:                     GNU AFFERO GENERAL PUBLIC LICENSE
License-File: LICENSE
License-File: LICENSE-COMMERCIAL.txt
Keywords: ai,development,documentation,framework,llm,mcp
Classifier: Development Status :: 4 - Beta
Classifier: Intended Audience :: Developers
Classifier: License :: OSI Approved :: MIT License
Classifier: Programming Language :: Python :: 3
Classifier: Programming Language :: Python :: 3.8
Classifier: Programming Language :: Python :: 3.9
Classifier: Programming Language :: Python :: 3.10
Classifier: Programming Language :: Python :: 3.11
Classifier: Programming Language :: Python :: 3.12
Classifier: Topic :: Scientific/Engineering :: Artificial Intelligence
Classifier: Topic :: Software Development :: Documentation
Classifier: Topic :: Software Development :: Libraries :: Python Modules
Requires-Python: >=3.12
Requires-Dist: aiosqlite>=0.19.0
Requires-Dist: alembic>=1.13.0
Requires-Dist: greenlet>=3.0.0
Requires-Dist: markdown>=3.5.0
Requires-Dist: mcp>=0.5.0
Requires-Dist: pydantic>=2.0.0
Requires-Dist: python-dotenv>=1.0.0
Requires-Dist: sqlmodel>=0.0.8
Requires-Dist: uvicorn[standard]>=0.24.0
Provides-Extra: dev
Requires-Dist: black>=23.0.0; extra == 'dev'
Requires-Dist: mypy>=1.0.0; extra == 'dev'
Requires-Dist: pytest-asyncio>=0.21.0; extra == 'dev'
Requires-Dist: pytest-cov>=4.1.0; extra == 'dev'
Requires-Dist: pytest>=7.0.0; extra == 'dev'
Requires-Dist: ruff>=0.1.0; extra == 'dev'
Provides-Extra: docs
Requires-Dist: mkdocs-material>=9.0.0; extra == 'docs'
Requires-Dist: mkdocs>=1.5.0; extra == 'docs'
Requires-Dist: weasyprint>=60.0; extra == 'docs'
